{
  "version": 2,
  "extractor": "papercropper",
  "figures": [
    {
      "url": "assets/figures/arxiv/2606.25161v1/fig-001.webp",
      "caption": "",
      "page": 0,
      "index": 1,
      "width": 1729,
      "height": 850,
      "label": "Figure"
    },
    {
      "url": "assets/figures/arxiv/2606.25161v1/fig-002.webp",
      "caption": "",
      "page": 0,
      "index": 2,
      "width": 1679,
      "height": 737,
      "label": "Figure"
    },
    {
      "url": "assets/figures/arxiv/2606.25161v1/fig-003.webp",
      "caption": "",
      "page": 0,
      "index": 3,
      "width": 1717,
      "height": 968,
      "label": "Figure"
    },
    {
      "url": "assets/figures/arxiv/2606.25161v1/fig-004.webp",
      "caption": "",
      "page": 0,
      "index": 4,
      "width": 1675,
      "height": 628,
      "label": "Figure"
    }
  ]
}