{
  "version": 2,
  "extractor": "papercropper",
  "tables": [
    {
      "url": "assets/tables/arxiv/2606.31504v1/table-001.webp",
      "caption": "",
      "page": 0,
      "index": 1,
      "width": 1649,
      "height": 1106,
      "label": "Table"
    },
    {
      "url": "assets/tables/arxiv/2606.31504v1/table-002.webp",
      "caption": "",
      "page": 0,
      "index": 2,
      "width": 491,
      "height": 198,
      "label": "Table"
    },
    {
      "url": "assets/tables/arxiv/2606.31504v1/table-003.webp",
      "caption": "",
      "page": 0,
      "index": 3,
      "width": 490,
      "height": 245,
      "label": "Table"
    },
    {
      "url": "assets/tables/arxiv/2606.31504v1/table-004.webp",
      "caption": "",
      "page": 0,
      "index": 4,
      "width": 495,
      "height": 157,
      "label": "Table"
    },
    {
      "url": "assets/tables/arxiv/2606.31504v1/table-005.webp",
      "caption": "",
      "page": 0,
      "index": 5,
      "width": 541,
      "height": 253,
      "label": "Table"
    },
    {
      "url": "assets/tables/arxiv/2606.31504v1/table-006.webp",
      "caption": "",
      "page": 0,
      "index": 6,
      "width": 1079,
      "height": 340,
      "label": "Table"
    },
    {
      "url": "assets/tables/arxiv/2606.31504v1/table-007.webp",
      "caption": "",
      "page": 0,
      "index": 7,
      "width": 1494,
      "height": 278,
      "label": "Table"
    },
    {
      "url": "assets/tables/arxiv/2606.31504v1/table-008.webp",
      "caption": "",
      "page": 0,
      "index": 8,
      "width": 1334,
      "height": 300,
      "label": "Table"
    },
    {
      "url": "assets/tables/arxiv/2606.31504v1/table-009.webp",
      "caption": "",
      "page": 0,
      "index": 9,
      "width": 477,
      "height": 265,
      "label": "Table"
    },
    {
      "url": "assets/tables/arxiv/2606.31504v1/table-010.webp",
      "caption": "",
      "page": 0,
      "index": 10,
      "width": 1499,
      "height": 296,
      "label": "Table"
    },
    {
      "url": "assets/tables/arxiv/2606.31504v1/table-011.webp",
      "caption": "",
      "page": 0,
      "index": 11,
      "width": 1595,
      "height": 523,
      "label": "Table"
    },
    {
      "url": "assets/tables/arxiv/2606.31504v1/table-012.webp",
      "caption": "",
      "page": 0,
      "index": 12,
      "width": 1596,
      "height": 440,
      "label": "Table"
    },
    {
      "url": "assets/tables/arxiv/2606.31504v1/table-013.webp",
      "caption": "",
      "page": 0,
      "index": 13,
      "width": 1661,
      "height": 633,
      "label": "Table"
    }
  ]
}